uw_restclients_sdbmyuw-1.5.dist-info/licenses/LICENSE
uw_sdbmyuw/VERSION
uw_sdbmyuw/__init__.py
uw_sdbmyuw/dao.py
uw_sdbmyuw/exceptions.py
uw_sdbmyuw/models.py
uw_sdbmyuw/test.py
uw_sdbmyuw/util.py
uw_sdbmyuw/resources/sdbmyuw/file/sdb_MyUW/appstatus.asp_s_000000001
uw_sdbmyuw/resources/sdbmyuw/file/sdb_MyUW/appstatus.asp_s_000000002
uw_sdbmyuw/resources/sdbmyuw/file/sdb_MyUW/appstatus.asp_s_000000003
uw_sdbmyuw/resources/sdbmyuw/file/sdb_MyUW/appstatus.asp_s_000000004
uw_sdbmyuw/resources/sdbmyuw/file/sdb_MyUW/appstatus.asp_s_000000005
uw_sdbmyuw/resources/sdbmyuw/file/sdb_MyUW/appstatus.asp_s_000000006
uw_sdbmyuw/resources/sdbmyuw/file/sdb_MyUW/appstatus.asp_s_000000007
uw_sdbmyuw/resources/sdbmyuw/file/sdb_MyUW/appstatus.asp_s_000000008
uw_sdbmyuw/resources/sdbmyuw/file/sdb_MyUW/appstatus.asp_s_000000009
uw_sdbmyuw/tests/__init__.py
uw_sdbmyuw/tests/test_appstatus.py
uw_sdbmyuw/tests/test_models.py
uw_restclients_sdbmyuw-1.5.dist-info/METADATA
uw_restclients_sdbmyuw-1.5.dist-info/WHEEL
uw_restclients_sdbmyuw-1.5.dist-info/top_level.txt
uw_restclients_sdbmyuw-1.5.dist-info/RECORD
